{"type":"View","props":{"width":1920,"height":1080},"compId":2,"child":[{"type":"Image","props":{"y":0,"x":0,"var":"imgbg","top":0,"skin":"commers/blackbg.png","sizeGrid":"3,3,3,3","right":0,"left":0,"bottom":0,"alpha":0.5},"compId":3},{"type":"Panel","props":{"x":0,"width":1920,"var":"mainpanel","top":0,"mouseThrough":true,"bottom":0},"compId":7,"child":[{"type":"Image","props":{"y":30,"x":30,"top":30,"skin":"uiCommonUpdate/radBg.png","sizeGrid":"3,3,3,3","right":30,"left":30,"bottom":30},"compId":11},{"type":"Label","props":{"var":"titlelbl","top":50,"text":"预览图","left":50,"fontSize":32,"font":"SimHei","color":"#262B2E"},"compId":18},{"type":"Panel","props":{"var":"contentPanel","vScrollBarSkin":"uiCommonUpdate/vscroll.png","top":95,"right":35,"left":35,"bottom":35},"compId":17,"child":[{"type":"Image","props":{"y":60,"x":175,"var":"img"},"compId":4}]},{"type":"Button","props":{"width":32,"var":"closeBtn","top":35,"stateNum":1,"skin":"uiCommonUpdate/closeBtn.png","right":40,"labelSize":24,"height":32},"compId":5}]},{"type":"Script","props":{"runtime":"script.workpanel.ImageEffectControlller"},"compId":19}],"loadList":["commers/blackbg.png","uiCommonUpdate/radBg.png","uiCommonUpdate/vscroll.png","uiCommonUpdate/closeBtn.png"],"loadList3D":[]}