{"type":"View","props":{"width":1920,"height":1080},"compId":2,"child":[{"type":"Image","props":{"y":10,"x":10,"top":0,"skin":"commers/blackbg.png","sizeGrid":"3,3,3,3","right":0,"left":0,"bottom":0,"alpha":0.5},"compId":3},{"type":"Panel","props":{"x":0,"width":1920,"var":"mainpanel","top":0,"bottom":0},"compId":4,"child":[{"type":"Image","props":{"y":10,"width":1860,"skin":"commers/commonpopbg.png","sizeGrid":"3,3,3,3","right":30,"left":30,"height":876},"compId":6,"child":[{"type":"Label","props":{"y":40,"x":30,"text":"设置材料和工艺-","fontSize":36,"font":"SimHei","color":"#030303","bold":true},"compId":9},{"type":"Label","props":{"y":40,"x":303,"text":"超幅拼接剪裁","fontSize":36,"font":"SimHei","color":"#003dc6","bold":true},"compId":28},{"type":"Image","props":{"y":125,"x":49,"width":1772,"skin":"uiCommonUpdate/grayFrame.png","sizeGrid":"2,2,2,2","height":638},"compId":29,"child":[{"type":"List","props":{"var":"productlist","vScrollBarSkin":"uiCommonUpdate/vscroll.png","top":80,"right":30,"left":30,"height":531,"bottom":10},"compId":24},{"type":"Label","props":{"y":13,"x":51,"width":300,"var":"maxtips","text":"（单份最大裁切宽度：149cm）","fontSize":18,"color":"#f32d2d","bold":true,"align":"left"},"compId":25},{"type":"Label","props":{"y":50,"x":51,"width":578,"text":"注意：非等份裁切会导致少量长度误差，如非必要，请尽量等份裁切","height":18,"fontSize":18,"color":"#f32d2d","bold":true,"align":"left"},"compId":26}]},{"type":"Sprite","props":{"y":791,"x":1550,"var":"okbtn"},"compId":15,"child":[{"type":"Button","props":{"y":0,"x":0,"width":271,"var":"btnok","skin":"uiCommonUpdate/greenBtn.png","labelSize":36,"labelFont":"SimHei","labelColors":"#FFFFFF,#FFFFFF,#FFFFFF,","label":"确认剪裁","height":66,"sizeGrid":"2,22,3,22"},"compId":16}]},{"type":"Button","props":{"width":32,"var":"closeBtn","top":41,"stateNum":1,"skin":"uiCommonUpdate/closeBtn.png","right":23,"height":32},"compId":30},{"type":"Text","props":{"y":824,"x":1420,"width":70,"var":"cancelBtn","text":"取消","presetID":1,"height":31,"fontSize":24,"font":"SimHei","color":"#003dc6","bold":true,"isPresetRoot":true,"runtime":"laya.display.Text"},"compId":31,"child":[{"type":"Script","props":{"presetID":2,"runtime":"script.prefabScript.LinkTextControl"},"compId":32}]}]}]},{"type":"Script","props":{"runtime":"script.order.InputCutNumControl"},"compId":23}],"loadList":["commers/blackbg.png","commers/commonpopbg.png","uiCommonUpdate/grayFrame.png","uiCommonUpdate/vscroll.png","uiCommonUpdate/greenBtn.png","uiCommonUpdate/closeBtn.png","prefabs/LinksText.prefab"],"loadList3D":[]}