{"type":"View","props":{"width":1624,"top":0,"right":0,"left":0,"height":1080,"bottom":0},"compId":2,"child":[{"type":"Image","props":{"y":0,"x":-296,"visible":false,"skin":"views/字牌首页.png"},"compId":112},{"type":"Image","props":{"top":0,"skin":"commers/blackbg.png","sizeGrid":"3,3,3,3","right":0,"left":0,"bottom":0,"alpha":0.5},"compId":3},{"type":"Panel","props":{"var":"panel_main","top":0,"right":0,"left":0,"bottom":120},"compId":4,"child":[{"type":"Image","props":{"top":0,"skin":"commers/commonpopbg.png","sizeGrid":"3,3,3,3","right":0,"left":0,"bottom":0},"compId":36},{"type":"Image","props":{"top":122,"skin":"commers/cutline.png","right":0,"left":0},"compId":143},{"type":"HBox","props":{"y":50,"x":271,"presetID":1,"space":38,"isPresetRoot":true},"compId":114,"child":[{"type":"Box","props":{"presetID":2,"var":"step1","name":"step1"},"compId":52,"child":[{"type":"Label","props":{"text":"字牌工艺设计","presetID":3,"color":"#003dc6","name":"lbl","fontSize":24,"font":"SimHei","bold":false},"compId":50},{"type":"Image","props":{"presetID":4,"sizeGrid":"3,12,3,10","y":39,"x":1,"skin":"uiCommonUpdate/underline.png","name":"underline"},"compId":51}]},{"type":"Box","props":{"presetID":5,"x":291,"var":"step2","name":"step2"},"compId":53,"child":[{"type":"Label","props":{"text":"设置打包方式","presetID":6,"color":"#003dc6","name":"lbl","fontSize":24,"font":"SimHei","bold":false},"compId":54},{"type":"Image","props":{"presetID":7,"sizeGrid":"3,12,3,10","y":39,"x":1,"skin":"uiCommonUpdate/underline.png","name":"underline"},"compId":55}]},{"type":"Box","props":{"y":0,"x":567,"width":99,"presetID":5,"height":51,"var":"step2","name":"step2"},"compId":145,"child":[{"type":"Label","props":{"text":"审核结算","presetID":6,"color":"#003dc6","name":"lbl","fontSize":24,"font":"SimHei","bold":false},"compId":146},{"type":"Image","props":{"width":100,"presetID":7,"sizeGrid":"3,12,3,10","y":39,"x":1,"skin":"uiCommonUpdate/underline.png","name":"underline"},"compId":147}]},{"type":"Box","props":{"y":0,"x":794,"presetID":11,"var":"step3","name":"step3"},"compId":59,"child":[{"type":"Label","props":{"text":"下单成功","presetID":12,"color":"#003dc6","name":"lbl","fontSize":24,"font":"SimHei","bold":false},"compId":60},{"type":"Image","props":{"presetID":13,"sizeGrid":"3,12,3,10","y":39,"x":1,"width":96,"skin":"uiCommonUpdate/underline.png","name":"underline"},"compId":61}]},{"type":"Image","props":{"presetID":17,"y":2.5,"x":194,"skin":"iconsNew/orderArrow.png"},"compId":66},{"type":"Image","props":{"presetID":18,"y":2.5,"x":476,"skin":"iconsNew/orderArrow.png"},"compId":67},{"type":"Image","props":{"y":2.5,"x":700,"skin":"iconsNew/orderArrow.png","presetID":19},"compId":68},{"type":"Script","props":{"stepNum":"5","step":1,"presetID":21,"enabled":true,"runtime":"script.prefabScript.OderTopFlowController"},"compId":70}]},{"type":"Button","props":{"y":8,"x":1886.5,"width":25,"var":"closebtn","skin":"commers/btnclose.png","height":25},"compId":24},{"type":"Panel","props":{"width":334,"top":128,"right":0,"bottom":0},"compId":72,"child":[{"type":"Label","props":{"y":10,"x":8,"text":"制作字牌类型","fontSize":24,"font":"SimHei","color":"#50575C"},"compId":141},{"type":"List","props":{"var":"productlist","vScrollBarSkin":"uiCommonUpdate/vscroll.png","top":57,"right":0,"left":13,"height":779,"bottom":0},"compId":106}]},{"type":"Box","props":{"y":128,"visible":false,"var":"leftOptPanel","right":342},"compId":113,"child":[{"type":"CheckBox","props":{"y":36,"x":8,"var":"lighton","skin":"upload1/imgselect.png","labelSize":20,"label":"发光"},"compId":109},{"type":"Label","props":{"y":121,"x":16,"width":50,"text":"厚度","height":14,"fontSize":18,"font":"SimHei"},"compId":19},{"type":"TextInput","props":{"y":113,"x":73,"width":128,"var":"depth1","type":"number","text":"TextInput","skin":"comp/textinput.png","height":30,"fontSize":20,"font":"SimHei","sizeGrid":"6,15,7,14"},"compId":20},{"type":"RadioGroup","props":{"y":82,"x":16,"width":171,"var":"mattype1","skin":"comp/radiogroup.png","labels":"PVC,亚克力","labelSize":18,"labelFont":"SimHei","height":24},"compId":21},{"type":"Button","props":{"y":213,"x":73,"width":100,"var":"createlayer1","skin":"comp/button.png","label":"第一层创建","height":30},"compId":22},{"type":"Label","props":{"y":152,"x":80,"width":82,"var":"choosecolor1","height":30,"borderColor":"#0d0d0d","bgColor":"#ef1111"},"compId":119},{"type":"Label","props":{"y":158,"x":16,"width":50,"text":"颜色","height":18,"fontSize":18,"font":"SimHei"},"compId":25},{"type":"Label","props":{"y":291,"x":16,"width":50,"text":"厚度","height":18,"fontSize":18,"font":"SimHei"},"compId":27},{"type":"TextInput","props":{"y":286,"x":73,"width":128,"var":"depth2","type":"number","text":"TextInput","skin":"comp/textinput.png","height":30,"fontSize":20,"font":"SimHei","sizeGrid":"6,15,7,14"},"compId":28},{"type":"RadioGroup","props":{"y":258,"x":16,"width":171,"var":"mattype2","skin":"comp/radiogroup.png","labels":"PVC,亚克力","labelSize":18,"labelFont":"SimHei","height":24,"direction":"horizontal"},"compId":29},{"type":"Button","props":{"y":391,"x":77,"width":100,"var":"createlayer2","skin":"comp/button.png","label":"第二层创建","height":30},"compId":30},{"type":"Label","props":{"y":332,"x":16,"width":50,"text":"颜色","height":18,"fontSize":18,"font":"SimHei"},"compId":31},{"type":"Label","props":{"y":612,"x":0,"width":50,"text":"大小(cm)","height":18,"fontSize":16,"font":"SimHei"},"compId":34},{"type":"TextInput","props":{"y":607,"x":68,"width":63,"var":"fontsizeinput","type":"number","text":"20","skin":"comp/textinput.png","height":30,"fontSize":20,"font":"SimHei","sizeGrid":"6,15,7,14"},"compId":35},{"type":"List","props":{"y":669,"x":5,"width":216,"var":"backimglist","spaceX":5,"repeatY":5,"repeatX":2,"height":160},"compId":37},{"type":"Label","props":{"y":646,"x":8,"width":86,"text":"选择背景：","height":18,"fontSize":18,"font":"SimHei"},"compId":38},{"type":"HSlider","props":{"y":194,"x":68,"width":134,"var":"alphasilder1","skin":"comp/hslider.png","min":0,"max":100,"height":14},"compId":39},{"type":"Label","props":{"y":188,"x":6,"width":50,"text":"透明度","height":18,"fontSize":18,"font":"SimHei"},"compId":40},{"type":"HSlider","props":{"y":369,"x":70,"width":134,"var":"alphasilder2","skin":"comp/hslider.png","min":0,"max":100,"height":14},"compId":41},{"type":"Label","props":{"y":363,"x":8,"width":50,"text":"透明度","height":18,"fontSize":18,"font":"SimHei"},"compId":42},{"type":"Label","props":{"y":460,"x":9,"width":50,"text":"厚度","height":18,"fontSize":18,"font":"SimHei"},"compId":43},{"type":"TextInput","props":{"y":455,"x":66,"width":128,"var":"depth3","type":"number","text":"TextInput","skin":"comp/textinput.png","height":30,"fontSize":20,"font":"SimHei","sizeGrid":"6,15,7,14"},"compId":44},{"type":"RadioGroup","props":{"y":427,"x":9,"width":171,"var":"mattype3","skin":"comp/radiogroup.png","labels":"PVC,亚克力","labelSize":18,"labelFont":"SimHei","height":24,"direction":"horizontal"},"compId":45},{"type":"Button","props":{"y":560,"x":70,"width":100,"var":"createlayer3","skin":"comp/button.png","label":"第三层创建","height":30},"compId":46},{"type":"Label","props":{"y":501,"x":9,"width":50,"text":"颜色","height":18,"fontSize":18,"font":"SimHei"},"compId":47},{"type":"HSlider","props":{"y":538,"x":63,"width":134,"var":"alphasilder3","skin":"comp/hslider.png","min":0,"max":100,"height":14},"compId":49},{"type":"Label","props":{"y":532,"x":1,"width":50,"text":"透明度","height":18,"fontSize":18,"font":"SimHei"},"compId":120},{"type":"Button","props":{"y":607,"x":137,"width":62,"var":"changSizeBtn","skin":"comp/button.png","label":"确定","height":30},"compId":121},{"type":"Label","props":{"y":326,"x":80,"width":82,"var":"choosecolor2","height":30,"borderColor":"#0d0d0d","bgColor":"#fdf8f8"},"compId":122},{"type":"Label","props":{"y":495,"x":77,"width":82,"var":"choosecolor3","height":30,"borderColor":"#0d0d0d","bgColor":"#090a09"},"compId":123},{"type":"Label","props":{"y":32,"x":153,"width":82,"var":"lightcolor","height":30,"borderColor":"#0d0d0d","bgColor":"#ef1111"},"compId":110},{"type":"Label","props":{"y":37,"x":89,"width":50,"text":"颜色","height":18,"fontSize":18,"font":"SimHei"},"compId":111},{"type":"Button","props":{"var":"closeOperate","top":0,"stateNum":1,"skin":"uiCommonUpdate/closeGray.png","right":5},"compId":144}]},{"type":"Image","props":{"y":128,"x":1300,"width":220,"visible":false,"var":"colorpanel","skin":"comp/blank.png","sizeGrid":"2,2,2,2","height":850,"alpha":1},"compId":115,"child":[{"type":"Image","props":{"top":8,"skin":"commers/commonpopbg.png","sizeGrid":"5,5,5,5","right":8,"left":8,"bottom":8},"compId":116},{"type":"List","props":{"x":18,"width":185,"var":"colorlist","top":38,"height":793,"bottom":19},"compId":117},{"type":"Button","props":{"y":12,"x":192,"var":"closecolor","skin":"commers/btnclose.png"},"compId":118}]},{"type":"Label","props":{"y":55.5,"x":49,"text":"字牌下单","fontSize":36,"font":"SimHei","bold":true},"compId":125}]},{"type":"Panel","props":{"var":"panelbottom","right":0,"left":0,"height":120,"bottom":0},"compId":88,"child":[{"type":"Box","props":{"y":0,"x":0,"right":0,"left":0,"height":120,"bottom":0},"compId":126,"child":[{"type":"Image","props":{"top":0,"skin":"uiCommonUpdate/btmBg.png","sizeGrid":"3,3,3,3","right":0,"left":0,"bottom":0},"compId":127},{"type":"Label","props":{"y":26,"x":194,"text":"12","fontSize":24,"font":"SimHei","color":"#f9f6f6","bold":true},"compId":128},{"type":"Label","props":{"y":72,"x":53,"text":"应付总额","fontSize":24,"font":"SimHei","color":"#f9f6f6"},"compId":129},{"type":"Label","props":{"y":66,"x":168,"text":"50.34","fontSize":36,"font":"SimHei","color":"#f9f6f6","bold":true},"compId":130},{"type":"Label","props":{"y":30,"x":541,"text":"优惠折扣（元）","fontSize":18,"font":"SimHei","color":"#f9f6f6"},"compId":131},{"type":"Label","props":{"y":26,"x":685,"text":"12","fontSize":24,"font":"SimHei","color":"#f9f6f6","bold":true},"compId":132},{"type":"Label","props":{"y":26,"x":391,"text":"47.25","fontSize":24,"font":"SimHei","color":"#f9f6f6","bold":true},"compId":133},{"type":"Label","props":{"y":30,"x":270,"text":"总费用（元）","fontSize":18,"font":"SimHei","color":"#f9f6f6"},"compId":134},{"type":"Label","props":{"y":30,"x":52,"text":"制作数量（件）","fontSize":18,"font":"SimHei","color":"#f9f6f6"},"compId":135},{"type":"Label","props":{"y":87,"text":"结算前请务必要核对确认 材料 尺寸 工艺 数量等信息","right":30,"fontSize":18,"font":"SimHei","color":"#f9f6f6","bold":true},"compId":136},{"type":"Button","props":{"y":20,"x":1380,"width":181,"skin":"uiCommonUpdate/greenBtn.png","labelSize":24,"labelFont":"SimHei","labelColors":"#FFFFFF,#FFFFFF,#FFFFFF","label":"去打包","height":44,"sizeGrid":"2,22,3,22"},"compId":140}]}]},{"type":"Script","props":{"runtime":"script.characterpaint.CharacterMainControl"},"compId":23}],"loadList":["views/字牌首页.png","commers/blackbg.png","commers/commonpopbg.png","commers/cutline.png","prefabs/OrderTopLine.prefab","iconsNew/orderArrow.png","commers/btnclose.png","uiCommonUpdate/vscroll.png","upload1/imgselect.png","comp/textinput.png","comp/radiogroup.png","comp/button.png","comp/hslider.png","uiCommonUpdate/closeGray.png","comp/blank.png","uiCommonUpdate/btmBg.png","uiCommonUpdate/greenBtn.png"],"loadList3D":[]}